otwstest/__init__.py
otwstest/schema/__init__.py
otwstest/schema/primitives.py
otwstest/schema/taxonomy/__init__.py
otwstest/schema/taxonomy/about.py
otwstest/schema/taxonomy/flags.py
otwstest/schema/taxonomy/lica.py
otwstest/schema/taxonomy/subtree.py
otwstest/schema/taxonomy/taxon.py
otwstest/schema/tnrs/__init__.py
otwstest/schema/tnrs/autocomplete_name.py
otwstest/schema/tnrs/infer_context.py
otwstest/schema/tnrs/match_names.py
otwstest/taxonomy/__init__.py
otwstest/taxonomy/about/__init__.py
otwstest/taxonomy/flags/__init__.py
otwstest/taxonomy/mrca/__init__.py
otwstest/taxonomy/subtree/__init__.py
otwstest/taxonomy/taxon/__init__.py
otwstest/tnrs/__init__.py
test_ot_ws-0.2.0.data/scripts/test-ot-ws
test_ot_ws-0.2.0.dist-info/METADATA
test_ot_ws-0.2.0.dist-info/RECORD
test_ot_ws-0.2.0.dist-info/WHEEL
test_ot_ws-0.2.0.dist-info/top_level.txt
