Metadata-Version: 2.1
Name: test-ot-ws
Version: 0.2.0
Summary: Library for testing whether or not the Open Tree of Life web services are functioning correctly
Home-page: https://github.com/OpenTreeOfLife/test-ot-ws
Author: Mark T. Holder and see CONTRIBUTORS.txt file
Author-email: mtholder@gmail.com
License: Copyright (c) 2018, the authors (see file CONTRIBUTORS)
Requires-Dist: requests (>=2.19.1)
Requires-Dist: jsonschema (>=2.6.0)
